pepsis_pidl/__init__.py
pepsis_pidl/skeleton.py
pepsis_pidl-0.1.dist-info/LICENSE.txt
pepsis_pidl-0.1.dist-info/METADATA
pepsis_pidl-0.1.dist-info/WHEEL
pepsis_pidl-0.1.dist-info/top_level.txt
pepsis_pidl-0.1.dist-info/RECORD
