Metadata-Version: 2.1
Name: pepsis-pidl
Version: 0.1
Summary: Add a short description here!
Home-page: https://gitlab.com/rogmon/pepsis-pidl
Author: Roger March
Author-email: roger@cadroot.com
License: Apache-2.0
Project-URL: Documentation, https://pyscaffold.org/
Platform: any
Classifier: Development Status :: 4 - Beta
Classifier: Programming Language :: Python
License-File: LICENSE.txt
Requires-Dist: importlib-metadata ; python_version < "3.8"
Provides-Extra: testing
Requires-Dist: setuptools ; extra == 'testing'
Requires-Dist: pytest ; extra == 'testing'
Requires-Dist: pytest-cov ; extra == 'testing'
